whiskey/__init__.py
whiskey/assets.py
whiskey/commands.py
whiskey/feeds.py
whiskey/flatpandoc.py
whiskey/formatter.py
whiskey/freeze.py
whiskey/helpers.py
whiskey/settings.py
whiskey/tasks.py
whiskey/templates.py
whiskey/views.py
whiskey_flask-0.8.1.dist-info/METADATA
whiskey_flask-0.8.1.dist-info/WHEEL
whiskey_flask-0.8.1.dist-info/top_level.txt
whiskey_flask-0.8.1.dist-info/RECORD
