Metadata-Version: 2.1
Name: whiskey-flask
Version: 0.8.1
Summary: Whiskey makes writing happen.
Home-page: https://github.com/nickwynja/whiskey
Author: Nick Wynja
Author-email: nick@nickwynja.com
License: UNKNOWN
Platform: UNKNOWN
Requires-Dist: flask
Requires-Dist: click
Requires-Dist: configparser
Requires-Dist: feedgen
Requires-Dist: flask-flatpages
Requires-Dist: frozen-flask
Requires-Dist: Flask-Babel
Requires-Dist: Jinja2
Requires-Dist: Markdown
Requires-Dist: MarkupSafe
Requires-Dist: panflute
Requires-Dist: Pygments
Requires-Dist: pytz
Requires-Dist: python-dotenv
Requires-Dist: pypandoc
Requires-Dist: weasyprint
